LICENSE
MANIFEST.in
README.md
setup.py
django_ajax_comments_xtd/__init__.py
django_ajax_comments_xtd/apps.py
django_ajax_comments_xtd/decorators.py
django_ajax_comments_xtd/urls.py
django_ajax_comments_xtd.egg-info/PKG-INFO
django_ajax_comments_xtd.egg-info/SOURCES.txt
django_ajax_comments_xtd.egg-info/dependency_links.txt
django_ajax_comments_xtd.egg-info/requires.txt
django_ajax_comments_xtd.egg-info/top_level.txt
django_ajax_comments_xtd/static/.gitignore
django_ajax_comments_xtd/static/django_ajax_comments_xtd/js/ajax_comments.es6
django_ajax_comments_xtd/static/django_ajax_comments_xtd/js/ajax_comments.js
django_ajax_comments_xtd/static/django_ajax_comments_xtd/js/ajax_comments.js.map
django_ajax_comments_xtd/templates/comments/form.html
django_ajax_comments_xtd/templates/comments/posted.html
django_ajax_comments_xtd/templates/django_comments_xtd/comment.html
django_ajax_comments_xtd/templates/django_comments_xtd/comment_tree.html